vvm/__init__.py
vvm/exceptions.py
vvm/install.py
vvm/main.py
vvm/wrapper.py
vvm/utils/__init__.py
vvm/utils/convert.py
vvm/utils/lock.py
vvm/utils/versioning.py
vvm-0.3.1.dist-info/LICENSE
vvm-0.3.1.dist-info/METADATA
vvm-0.3.1.dist-info/WHEEL
vvm-0.3.1.dist-info/top_level.txt
vvm-0.3.1.dist-info/RECORD
