Metadata-Version: 2.1
Name: vvm
Version: 0.3.1
Summary: Vyper version management tool
Home-page: https://github.com/vyperlang/vvm
Author: Ben Hauser
Author-email: ben@hauser.id
License: MIT
Keywords: ethereum vyper
Classifier: Intended Audience :: Developers
Classifier: License :: OSI Approved :: MIT License
Classifier: Natural Language :: English
Classifier: Programming Language :: Python :: 3
Classifier: Programming Language :: Python :: 3.6
Classifier: Programming Language :: Python :: 3.7
Classifier: Programming Language :: Python :: 3.8
Classifier: Programming Language :: Python :: 3.9
Classifier: Programming Language :: Python :: 3.10
Classifier: Programming Language :: Python :: 3.11
Requires-Python: >=3.8, <4
License-File: LICENSE
Requires-Dist: requests <3,>=2.32.3
Requires-Dist: packaging <25,>=23.1
